webdev_pitfall_analyzer/__init__.py
webdev_pitfall_analyzer/main.py
webdev_pitfall_analyzer/prompts.py
webdev_pitfall_analyzer-2025.12.21133820.dist-info/METADATA
webdev_pitfall_analyzer-2025.12.21133820.dist-info/WHEEL
webdev_pitfall_analyzer-2025.12.21133820.dist-info/top_level.txt
webdev_pitfall_analyzer-2025.12.21133820.dist-info/RECORD
