Metadata-Version: 2.4
Name: webdev-pitfall-analyzer
Version: 2025.12.21133820
Summary: This package helps users identify and avoid common pitfalls in web and HTML development by analyzing text-based input—like code snippets, design descriptions, or technical discussions—and returning a
Author-email: webdev-pitfall-analyzer <hi@eugene.plus>
License: MIT
Project-URL: Homepage, https://github.com/chigwell/webdev-pitfall-analyzer
Requires-Python: >=3.9
Requires-Dist: langchain-llm7>=0.0.0
Requires-Dist: llmatch-messages>=0.0.0
Requires-Dist: langchain-core>=0.3.0
